app/__init__.py
app/backend.py
gimmick/__init__.py
gimmick/constants.py
gimmick/distributer.py
gimmick/mapping.py
gimmick/image_op/__init__.py
gimmick/image_op/functions.py
gimmick/models/__init__.py
gimmick/models/autoencoder.py
gimmick/models/autoencoder_cnn.py
gimmick/models/autoencoder_cnn_variational.py
gimmick/models/autoencoder_dense.py
gimmick/models/autoencoder_lstm.py
gimmick/models/ganmod/__init__.py
gimmick/models/ganmod/gan.py
gimmick-1.0.dist-info/LICENSE
gimmick-1.0.dist-info/METADATA
gimmick-1.0.dist-info/WHEEL
gimmick-1.0.dist-info/top_level.txt
gimmick-1.0.dist-info/RECORD
