Metadata-Version: 2.1
Name: gimmick
Version: 1.0
Summary: Libraray contains algo to generate images by learning representation from data
Home-page: https://github.com/pankajr141/gimmick
Author: Pankaj Rawat
Author-email: pankajr141@gmail.com
License: UNKNOWN
Platform: UNKNOWN
Classifier: Programming Language :: Python :: 3
Classifier: License :: OSI Approved :: Apache Software License
Classifier: Operating System :: OS Independent
License-File: LICENSE
Requires-Dist: docutils (==0.15.2)
Requires-Dist: h5py (==2.10.0)
Requires-Dist: pandas (==1.2.2)
Requires-Dist: scikit-learn (==0.24.2)
Requires-Dist: Sphinx (==3.5.4)
Requires-Dist: sphinx-rtd-theme (==0.5.2)
Requires-Dist: sphinxcontrib-applehelp (==1.0.2)
Requires-Dist: sphinxcontrib-devhelp (==1.0.2)
Requires-Dist: sphinxcontrib-htmlhelp (==2.0.0)
Requires-Dist: sphinxcontrib-jsmath (==1.0.1)
Requires-Dist: sphinxcontrib-qthelp (==1.0.3)
Requires-Dist: sphinxcontrib-serializinghtml (==1.1.5)
Requires-Dist: streamlit (==1.0.0)
Requires-Dist: tensorflow (==2.3.0)
Requires-Dist: zipp (==3.1.0)
Requires-Dist: opencv-python (==4.2.0.34)
Requires-Dist: tqdm (==4.48.2)
Requires-Dist: matplotlib (==3.2.1)
